VoxelFarmClient/__init__.py
VoxelFarmClient/voxelfarmclient.py
client/__init__.py
client/voxelfarmclient.py
VoxelFarmClient-0.0.4.dist-info/LICENSE
VoxelFarmClient-0.0.4.dist-info/METADATA
VoxelFarmClient-0.0.4.dist-info/WHEEL
VoxelFarmClient-0.0.4.dist-info/top_level.txt
VoxelFarmClient-0.0.4.dist-info/RECORD
