Metadata-Version: 2.1
Name: VoxelFarmClient
Version: 0.0.4
Summary: voxelfarm client
Home-page: https://www.voxelfarm.com/help/PythonCookbook.html
Author: voxelfarm suport
Author-email: contant@voxelfarm.com
License: UNKNOWN
Project-URL: Bug Tracker, https://github.com/voxelfarm/voxelfarmclient/issues
Platform: UNKNOWN
Classifier: Programming Language :: Python :: 3
Classifier: License :: OSI Approved :: MIT License
Classifier: Operating System :: OS Independent
Requires-Python: >=3.7
License-File: LICENSE
Requires-Dist: pandas
Provides-Extra: dev
Requires-Dist: pytest (>=3.7) ; extra == 'dev'
